textanalysis_python_sdk/__init__.py
textanalysis_python_sdk/entity.py
textanalysis_python_sdk/enumtypes.py
textanalysis_python_sdk/exception.py
textanalysis_python_sdk/sentence.py
textanalysis_python_sdk/textanalysis.py
textanalysis_python_sdk/textanalysisanswer.py
neticle_textanalysis_api_sdk-3.0.0.dist-info/LICENSE
neticle_textanalysis_api_sdk-3.0.0.dist-info/METADATA
neticle_textanalysis_api_sdk-3.0.0.dist-info/WHEEL
neticle_textanalysis_api_sdk-3.0.0.dist-info/top_level.txt
neticle_textanalysis_api_sdk-3.0.0.dist-info/RECORD
