Metadata-Version: 2.1
Name: neticle-textanalysis-api-sdk
Version: 3.0.0
Summary: Python SDK for Neticle Text Analysis API
Home-page: https://neticle.com/textanalysisapi/en/
Author: Neticle
Author-email: dev@neticle.com
License: MIT
Keywords: nlp,natural language processing,text analysis,sentiment analysis,topic recognition
Platform: UNKNOWN
Classifier: Programming Language :: Python :: 3
Classifier: License :: OSI Approved :: MIT License
Classifier: Operating System :: OS Independent
Requires-Python: >= 3.7
Requires-Dist: requests
